hnswindex/__init__.py
hnswindex/bindings.py
hnswindex/sync_libs.py
hnswindex/artifacts/native/win-x64/HNSWIndex.Native.dll
hnswindex-1.6.0.dist-info/licenses/LICENSE
hnswindex-1.6.0.dist-info/METADATA
hnswindex-1.6.0.dist-info/WHEEL
hnswindex-1.6.0.dist-info/top_level.txt
hnswindex-1.6.0.dist-info/RECORD
