Metadata-Version: 2.4
Name: hnswindex
Version: 1.6.0
Summary: HNSWIndex.Net python module
Author: Mateusz Skarupski (Skaipi)
License: MIT
Requires-Python: >=3.9
License-File: LICENSE
Requires-Dist: numpy>=1.22
Dynamic: license-file
